{
    "value": 39725,
    "4688": "hwangbroxd",
    "1608": "hwangbroxd",
    "266": "hwangbroxd",
    "374": "hwangbroxd",
    "3973": "hwangbroxd",
    "3220": "hwangbroxd",
    "4801": "hwangbroxd",
    "2893": "hwangbroxd",
    "4184": "hwangbroxd",
    "930": "hwangbroxd",
    "1741": "hwangbroxd",
    "2430": "hwangbroxd",
    "1508": "hwangbroxd",
    "1062": "hwangbroxd",
    "3303": "hwangbroxd",
    "4188": "hwangbroxd",
    "4277": "hwangbroxd",
    "2214": "hwangbroxd",
    "3812": "hwangbroxd",
    "3504": "hwangbroxd",
    "413": "hwangbroxd",
    "84": "hwangbroxd",
    "1815": "hwangbroxd",
    "3453": "hwangbroxd",
    "3089": "hwangbroxd",
    "4629": "hwangbroxd",
    "9": "hwangbroxd",
    "118": "hwangbroxd",
    "4402": "hwangbroxd",
    "454": "hwangbroxd",
    "4254": "hwangbroxd",
    "1899": "hwangbroxd",
    "3618": "hwangbroxd",
    "3503": "hwangbroxd",
    "561": "hwangbroxd",
    "1599": "hwangbroxd",
    "906": "hwangbroxd",
    "1033": "hwangbroxd",
    "134": "hwangbroxd",
    "201": "hwangbroxd",
    "343": "hwangbroxd",
    "3346": "hwangbroxd",
    "1763": "hwangbroxd",
    "3897": "hwangbroxd",
    "2784": "hwangbroxd",
    "4448": "hwangbroxd",
    "4547": "hwangbroxd",
    "1193": "hwangbroxd",
    "2877": "hwangbroxd",
    "4933": "hwangbroxd",
    "4248": "hwangbroxd",
    "3127": "hwangbroxd",
    "2940": "hwangbroxd",
    "4596": "hwangbroxd",
    "1063": "hwangbroxd",
    "4242": "hwangbroxd",
    "2013": "hwangbroxd",
    "2157": "hwangbroxd",
    "4234": "hwangbroxd",
    "951": "hwangbroxd",
    "3143": "hwangbroxd",
    "308": "hwangbroxd",
    "314": "hwangbroxd",
    "3724": "hwangbroxd",
    "2523": "hwangbroxd",
    "4831": "hwangbroxd",
    "3244": "hwangbroxd",
    "42": "hwangbroxd",
    "3033": "hwangbroxd",
    "2462": "hwangbroxd",
    "1970": "hwangbroxd",
    "4404": "hwangbroxd",
    "4046": "hwangbroxd",
    "2498": "hwangbroxd",
    "3625": "hwangbroxd",
    "2298": "hwangbroxd",
    "4884": "hwangbroxd",
    "3807": "hwangbroxd",
    "1543": "hwangbroxd",
    "2136": "hwangbroxd",
    "4924": "hwangbroxd",
    "2875": "hwangbroxd",
    "596": "hwangbroxd",
    "3427": "hwangbroxd",
    "2030": "hwangbroxd",
    "2593": "hwangbroxd",
    "359": "hwangbroxd",
    "102": "hwangbroxd",
    "3664": "hwangbroxd",
    "1998": "hwangbroxd",
    "1214": "hwangbroxd",
    "2550": "hwangbroxd",
    "2874": "hwangbroxd",
    "3983": "hwangbroxd",
    "4502": "hwangbroxd",
    "2243": "hwangbroxd",
    "2851": "hwangbroxd",
    "1980": "hwangbroxd",
    "4956": "hwangbroxd",
    "496": "hwangbroxd",
    "3533": "hwangbroxd",
    "1259": "hwangbroxd",
    "3502": "hwangbroxd",
    "1911": "hwangbroxd",
    "4636": "hwangbroxd",
    "1257": "hwangbroxd",
    "4669": "hwangbroxd",
    "316": "hwangbroxd",
    "2610": "hwangbroxd",
    "1179": "hwangbroxd",
    "3956": "hwangbroxd",
    "1107": "hwangbroxd",
    "3058": "hwangbroxd",
    "1416": "hwangbroxd",
    "4968": "hwangbroxd",
    "1462": "hwangbroxd",
    "4687": "hwangbroxd",
    "166": "hwangbroxd",
    "1578": "hwangbroxd",
    "909": "hwangbroxd",
    "4799": "hwangbroxd",
    "145": "hwangbroxd",
    "3041": "hwangbroxd",
    "2519": "hwangbroxd",
    "2571": "hwangbroxd",
    "3662": "hwangbroxd",
    "2313": "hwangbroxd",
    "1898": "hwangbroxd",
    "2669": "hwangbroxd",
    "2482": "hwangbroxd",
    "236": "hwangbroxd",
    "3067": "hwangbroxd",
    "671": "hwangbroxd",
    "4627": "hwangbroxd",
    "668": "hwangbroxd",
    "823": "hwangbroxd",
    "3399": "hwangbroxd",
    "443": "hwangbroxd",
    "1774": "hwangbroxd",
    "2367": "hwangbroxd",
    "2111": "hwangbroxd",
    "3328": "hwangbroxd",
    "341": "hwangbroxd",
    "2514": "hwangbroxd",
    "297": "hwangbroxd",
    "2932": "hwangbroxd",
    "2656": "hwangbroxd",
    "4009": "hwangbroxd",
    "770": "hwangbroxd",
    "2750": "hwangbroxd",
    "4141": "hwangbroxd",
    "4722": "hwangbroxd",
    "2294": "hwangbroxd",
    "3273": "hwangbroxd",
    "2112": "hwangbroxd",
    "3866": "hwangbroxd",
    "4163": "hwangbroxd",
    "3122": "hwangbroxd",
    "1399": "hwangbroxd",
    "2507": "hwangbroxd",
    "2885": "hwangbroxd",
    "4741": "hwangbroxd",
    "2861": "hwangbroxd",
    "862": "hwangbroxd",
    "3374": "hwangbroxd",
    "1286": "hwangbroxd",
    "4693": "hwangbroxd",
    "4618": "hwangbroxd",
    "1920": "hwangbroxd",
    "3115": "hwangbroxd",
    "2272": "hwangbroxd",
    "734": "hwangbroxd",
    "2281": "hwangbroxd",
    "1974": "hwangbroxd",
    "633": "hwangbroxd",
    "2452": "hwangbroxd",
    "253": "hwangbroxd",
    "3039": "hwangbroxd",
    "3102": "hwangbroxd",
    "3279": "hwangbroxd",
    "3932": "hwangbroxd",
    "3930": "hwangbroxd",
    "3695": "hwangbroxd",
    "2634": "hwangbroxd",
    "1714": "hwangbroxd",
    "3584": "hwangbroxd",
    "963": "hwangbroxd",
    "3785": "hwangbroxd",
    "1184": "hwangbroxd",
    "4833": "hwangbroxd",
    "1922": "hwangbroxd",
    "3549": "hwangbroxd",
    "3547": "hwangbroxd",
    "3573": "hwangbroxd",
    "3913": "hwangbroxd",
    "2679": "hwangbroxd",
    "4127": "hwangbroxd",
    "593": "hwangbroxd",
    "1836": "hwangbroxd",
    "4202": "hwangbroxd",
    "1633": "hwangbroxd",
    "4055": "hwangbroxd",
    "2160": "hwangbroxd",
    "4521": "hwangbroxd",
    "3466": "hwangbroxd",
    "3997": "hwangbroxd",
    "2835": "hwangbroxd",
    "3324": "hwangbroxd",
    "1357": "hwangbroxd",
    "619": "hwangbroxd",
    "4151": "hwangbroxd",
    "3944": "hwangbroxd",
    "251": "hwangbroxd",
    "3935": "hwangbroxd",
    "3893": "hwangbroxd",
    "2868": "hwangbroxd",
    "3687": "hwangbroxd",
    "4563": "hwangbroxd",
    "2906": "hwangbroxd",
    "3338": "hwangbroxd",
    "3985": "hwangbroxd",
    "2199": "hwangbroxd",
    "3919": "hwangbroxd",
    "886": "hwangbroxd",
    "1785": "hwangbroxd",
    "207": "hwangbroxd",
    "3754": "hwangbroxd",
    "46": "hwangbroxd",
    "1945": "hwangbroxd",
    "4332": "hwangbroxd",
    "449": "hwangbroxd",
    "4893": "hwangbroxd",
    "1797": "hwangbroxd",
    "3482": "hwangbroxd",
    "1916": "hwangbroxd",
    "1162": "hwangbroxd",
    "2265": "hwangbroxd",
    "1505": "hwangbroxd",
    "828": "hwangbroxd",
    "4420": "hwangbroxd",
    "3236": "hwangbroxd",
    "3580": "hwangbroxd",
    "2783": "hwangbroxd",
    "3128": "hwangbroxd",
    "4586": "hwangbroxd",
    "1143": "hwangbroxd",
    "1752": "hwangbroxd",
    "3598": "hwangbroxd",
    "312": "hwangbroxd",
    "2570": "hwangbroxd",
    "1510": "hwangbroxd",
    "2609": "hwangbroxd",
    "4940": "hwangbroxd",
    "2698": "hwangbroxd",
    "4551": "hwangbroxd",
    "3300": "hwangbroxd",
    "742": "hwangbroxd",
    "1437": "hwangbroxd",
    "144": "hwangbroxd",
    "412": "hwangbroxd",
    "350": "hwangbroxd",
    "2963": "hwangbroxd",
    "2105": "hwangbroxd",
    "2772": "hwangbroxd",
    "2257": "hwangbroxd",
    "787": "hwangbroxd",
    "4859": "hwangbroxd",
    "2017": "hwangbroxd",
    "4017": "hwangbroxd",
    "4748": "hwangbroxd",
    "893": "hwangbroxd",
    "1894": "hwangbroxd",
    "2573": "hwangbroxd",
    "4614": "hwangbroxd",
    "3231": "hwangbroxd",
    "2106": "hwangbroxd",
    "3857": "hwangbroxd",
    "509": "hwangbroxd",
    "1365": "hwangbroxd",
    "1551": "hwangbroxd",
    "3946": "hwangbroxd",
    "1802": "hwangbroxd",
    "3548": "hwangbroxd",
    "3247": "hwangbroxd",
    "4738": "hwangbroxd",
    "3963": "hwangbroxd",
    "1285": "hwangbroxd",
    "2049": "hwangbroxd",
    "1719": "hwangbroxd",
    "208": "hwangbroxd",
    "2666": "hwangbroxd",
    "3659": "hwangbroxd",
    "422": "hwangbroxd",
    "3674": "hwangbroxd",
    "952": "hwangbroxd",
    "1856": "hwangbroxd",
    "2066": "hwangbroxd",
    "4743": "hwangbroxd",
    "536": "hwangbroxd",
    "3121": "hwangbroxd",
    "3170": "hwangbroxd",
    "3345": "hwangbroxd",
    "3105": "hwangbroxd",
    "1264": "hwangbroxd",
    "651": "hwangbroxd",
    "2847": "hwangbroxd",
    "834": "hwangbroxd",
    "151": "hwangbroxd",
    "3563": "hwangbroxd",
    "2757": "hwangbroxd",
    "3135": "hwangbroxd",
    "4187": "hwangbroxd",
    "3906": "hwangbroxd",
    "4027": "hwangbroxd",
    "1442": "hwangbroxd",
    "2577": "hwangbroxd",
    "1251": "hwangbroxd",
    "492": "hwangbroxd",
    "3558": "hwangbroxd",
    "2292": "hwangbroxd",
    "4115": "hwangbroxd",
    "1886": "hwangbroxd",
    "2431": "hwangbroxd",
    "2150": "hwangbroxd",
    "4199": "hwangbroxd",
    "2544": "hwangbroxd",
    "726": "hwangbroxd",
    "4292": "hwangbroxd",
    "2540": "hwangbroxd",
    "738": "hwangbroxd",
    "3483": "hwangbroxd",
    "2676": "hwangbroxd",
    "3164": "hwangbroxd",
    "1159": "hwangbroxd",
    "2628": "hwangbroxd",
    "1507": "hwangbroxd",
    "4105": "hwangbroxd",
    "2054": "hwangbroxd",
    "4557": "hwangbroxd",
    "591": "hwangbroxd",
    "177": "hwangbroxd",
    "294": "hwangbroxd",
    "3814": "hwangbroxd",
    "1807": "hwangbroxd",
    "2148": "hwangbroxd",
    "3645": "hwangbroxd",
    "1526": "hwangbroxd",
    "4267": "hwangbroxd",
    "829": "hwangbroxd",
    "4670": "hwangbroxd",
    "4356": "hwangbroxd",
    "1303": "hwangbroxd",
    "976": "hwangbroxd",
    "2426": "hwangbroxd",
    "1246": "hwangbroxd",
    "949": "hwangbroxd",
    "4423": "hwangbroxd",
    "2139": "hwangbroxd",
    "1769": "hwangbroxd",
    "4355": "hwangbroxd",
    "1530": "hwangbroxd",
    "1393": "hwangbroxd",
    "120": "hwangbroxd",
    "984": "hwangbroxd",
    "4305": "hwangbroxd",
    "879": "hwangbroxd",
    "4542": "hwangbroxd",
    "2034": "hwangbroxd",
    "2617": "hwangbroxd",
    "3278": "hwangbroxd",
    "4988": "hwangbroxd",
    "1104": "hwangbroxd",
    "1869": "hwangbroxd",
    "2936": "hwangbroxd",
    "791": "hwangbroxd",
    "3455": "hwangbroxd",
    "2287": "hwangbroxd",
    "3495": "hwangbroxd",
    "926": "hwangbroxd",
    "183": "hwangbroxd",
    "3048": "hwangbroxd",
    "3613": "hwangbroxd",
    "3742": "hwangbroxd",
    "198": "hwangbroxd",
    "2807": "hwangbroxd",
    "1043": "hwangbroxd",
    "2121": "hwangbroxd",
    "4154": "hwangbroxd",
    "1768": "hwangbroxd",
    "1228": "hwangbroxd",
    "4398": "hwangbroxd",
    "2024": "hwangbroxd",
    "3576": "hwangbroxd",
    "1946": "hwangbroxd",
    "4662": "hwangbroxd",
    "1930": "hwangbroxd",
    "3179": "hwangbroxd",
    "4883": "hwangbroxd",
    "4395": "hwangbroxd",
    "3031": "hwangbroxd",
    "3592": "hwangbroxd",
    "1419": "hwangbroxd",
    "1630": "hwangbroxd",
    "4284": "hwangbroxd",
    "2028": "hwangbroxd",
    "1247": "hwangbroxd",
    "4568": "hwangbroxd",
    "4063": "hwangbroxd",
    "2702": "hwangbroxd",
    "3716": "hwangbroxd",
    "1439": "hwangbroxd",
    "3506": "hwangbroxd",
    "1389": "hwangbroxd",
    "2269": "hwangbroxd",
    "1236": "hwangbroxd",
    "148": "hwangbroxd",
    "2353": "hwangbroxd",
    "4675": "hwangbroxd",
    "1969": "hwangbroxd",
    "4855": "hwangbroxd",
    "3429": "hwangbroxd",
    "2633": "hwangbroxd",
    "2458": "hwangbroxd",
    "4725": "hwangbroxd",
    "2896": "hwangbroxd",
    "3608": "hwangbroxd",
    "1134": "hwangbroxd",
    "1018": "hwangbroxd",
    "1205": "hwangbroxd",
    "631": "hwangbroxd",
    "2224": "hwangbroxd",
    "1322": "hwangbroxd",
    "4276": "hwangbroxd",
    "3307": "hwangbroxd",
    "2463": "hwangbroxd",
    "2420": "hwangbroxd",
    "1547": "hwangbroxd",
    "4954": "hwangbroxd",
    "4073": "hwangbroxd",
    "1939": "hwangbroxd",
    "3005": "hwangbroxd",
    "3571": "hwangbroxd",
    "4030": "hwangbroxd",
    "95": "hwangbroxd",
    "2005": "hwangbroxd",
    "2227": "hwangbroxd",
    "2803": "hwangbroxd",
    "3438": "hwangbroxd",
    "2808": "hwangbroxd",
    "3201": "hwangbroxd",
    "1318": "hwangbroxd",
    "1130": "hwangbroxd",
    "3554": "hwangbroxd",
    "4280": "hwangbroxd",
    "2256": "hwangbroxd",
    "414": "hwangbroxd",
    "4905": "hwangbroxd",
    "1629": "hwangbroxd",
    "4570": "hwangbroxd",
    "2453": "hwangbroxd",
    "4239": "hwangbroxd",
    "324": "hwangbroxd",
    "4233": "hwangbroxd",
    "4794": "hwangbroxd",
    "4467": "hwangbroxd",
    "1777": "hwangbroxd",
    "320": "hwangbroxd",
    "155": "hwangbroxd",
    "4982": "hwangbroxd",
    "815": "hwangbroxd",
    "4033": "hwangbroxd",
    "2766": "hwangbroxd",
    "534": "hwangbroxd",
    "3962": "hwangbroxd",
    "2897": "hwangbroxd",
    "1362": "hwangbroxd",
    "1996": "hwangbroxd",
    "2234": "hwangbroxd",
    "2748": "hwangbroxd",
    "3856": "hwangbroxd",
    "2481": "hwangbroxd",
    "2843": "hwangbroxd",
    "1022": "hwangbroxd",
    "2522": "hwangbroxd",
    "4066": "hwangbroxd",
    "1308": "hwangbroxd",
    "812": "hwangbroxd",
    "2992": "hwangbroxd",
    "814": "hwangbroxd",
    "1433": "hwangbroxd",
    "1544": "hwangbroxd",
    "4262": "hwangbroxd",
    "1555": "hwangbroxd",
    "2654": "hwangbroxd",
    "39": "hwangbroxd",
    "817": "hwangbroxd",
    "2031": "hwangbroxd",
    "1823": "hwangbroxd",
    "1309": "hwangbroxd",
    "1567": "hwangbroxd",
    "2331": "hwangbroxd",
    "4144": "hwangbroxd",
    "4375": "hwangbroxd",
    "4285": "hwangbroxd",
    "2606": "hwangbroxd",
    "2872": "hwangbroxd",
    "1265": "hwangbroxd",
    "4157": "hwangbroxd",
    "285": "hwangbroxd",
    "223": "hwangbroxd",
    "1071": "hwangbroxd",
    "968": "hwangbroxd",
    "1082": "hwangbroxd",
    "1707": "hwangbroxd",
    "575": "hwangbroxd",
    "4194": "hwangbroxd",
    "2308": "hwangbroxd",
    "1413": "hwangbroxd",
    "3786": "hwangbroxd",
    "3360": "hwangbroxd",
    "444": "hwangbroxd",
    "1180": "hwangbroxd",
    "2015": "hwangbroxd",
    "3169": "hwangbroxd",
    "3398": "hwangbroxd",
    "2406": "hwangbroxd",
    "4149": "hwangbroxd",
    "4805": "hwangbroxd",
    "607": "hwangbroxd",
    "4585": "hwangbroxd",
    "703": "hwangbroxd",
    "718": "hwangbroxd",
    "4478": "hwangbroxd",
    "587": "hwangbroxd",
    "1380": "hwangbroxd",
    "1641": "hwangbroxd",
    "3271": "hwangbroxd",
    "2901": "hwangbroxd",
    "2443": "hwangbroxd",
    "3046": "hwangbroxd",
    "366": "hwangbroxd",
    "3840": "hwangbroxd",
    "389": "hwangbroxd",
    "849": "hwangbroxd",
    "2797": "hwangbroxd",
    "821": "hwangbroxd",
    "994": "hwangbroxd",
    "467": "hwangbroxd",
    "4613": "hwangbroxd",
    "4222": "hwangbroxd",
    "705": "hwangbroxd",
    "4070": "hwangbroxd",
    "1447": "hwangbroxd",
    "2249": "hwangbroxd",
    "3922": "hwangbroxd",
    "2379": "hwangbroxd",
    "4928": "hwangbroxd",
    "4353": "hwangbroxd",
    "3869": "hwangbroxd",
    "3312": "hwangbroxd",
    "522": "hwangbroxd",
    "1695": "hwangbroxd",
    "899": "hwangbroxd",
    "4934": "hwangbroxd",
    "840": "hwangbroxd",
    "620": "hwangbroxd",
    "550": "hwangbroxd",
    "2995": "hwangbroxd",
    "3749": "hwangbroxd",
    "2040": "hwangbroxd",
    "3940": "hwangbroxd",
    "1550": "hwangbroxd",
    "1637": "hwangbroxd",
    "3923": "hwangbroxd",
    "1044": "hwangbroxd",
    "3519": "hwangbroxd",
    "1245": "hwangbroxd",
    "1431": "hwangbroxd",
    "1997": "hwangbroxd",
    "771": "hwangbroxd",
    "2046": "hwangbroxd",
    "4452": "hwangbroxd",
    "3026": "hwangbroxd",
    "711": "hwangbroxd",
    "3052": "hwangbroxd",
    "4645": "hwangbroxd",
    "4314": "hwangbroxd",
    "40": "hwangbroxd",
    "1828": "hwangbroxd",
    "2217": "hwangbroxd",
    "578": "hwangbroxd",
    "302": "hwangbroxd",
    "4484": "hwangbroxd",
    "2579": "hwangbroxd",
    "3140": "hwangbroxd",
    "2967": "hwangbroxd",
    "3590": "hwangbroxd",
    "1029": "hwangbroxd",
    "4706": "hwangbroxd",
    "4667": "hwangbroxd",
    "3806": "hwangbroxd",
    "1344": "hwangbroxd",
    "2410": "hwangbroxd",
    "2781": "hwangbroxd",
    "2747": "hwangbroxd",
    "4196": "hwangbroxd",
    "1478": "hwangbroxd",
    "1438": "hwangbroxd",
    "1091": "hwangbroxd",
    "3138": "hwangbroxd",
    "2653": "hwangbroxd",
    "2009": "hwangbroxd",
    "1919": "hwangbroxd",
    "1910": "hwangbroxd",
    "432": "hwangbroxd",
    "1903": "hwangbroxd",
    "3970": "hwangbroxd",
    "2276": "hwangbroxd",
    "4354": "hwangbroxd",
    "1646": "hwangbroxd",
    "2208": "hwangbroxd",
    "691": "hwangbroxd",
    "929": "hwangbroxd",
    "154": "hwangbroxd",
    "4156": "hwangbroxd",
    "2760": "hwangbroxd",
    "3512": "hwangbroxd",
    "2587": "hwangbroxd",
    "1441": "hwangbroxd",
    "8": "hwangbroxd",
    "3037": "hwangbroxd",
    "4654": "hwangbroxd",
    "3366": "hwangbroxd",
    "2326": "hwangbroxd",
    "3457": "hwangbroxd",
    "1758": "hwangbroxd",
    "2501": "hwangbroxd",
    "2776": "hwangbroxd",
    "605": "hwangbroxd",
    "2830": "hwangbroxd",
    "4005": "hwangbroxd",
    "2792": "hwangbroxd",
    "3476": "hwangbroxd",
    "2905": "hwangbroxd",
    "3084": "hwangbroxd",
    "573": "hwangbroxd",
    "4281": "hwangbroxd",
    "1101": "hwangbroxd",
    "1792": "hwangbroxd",
    "1005": "hwangbroxd",
    "3885": "hwangbroxd",
    "4776": "hwangbroxd",
    "4037": "hwangbroxd",
    "3507": "hwangbroxd",
    "4313": "hwangbroxd",
    "4026": "hwangbroxd",
    "896": "hwangbroxd",
    "3445": "hwangbroxd",
    "4412": "hwangbroxd",
    "2837": "hwangbroxd",
    "1731": "hwangbroxd",
    "1942": "hwangbroxd",
    "4098": "hwangbroxd",
    "435": "hwangbroxd",
    "219": "hwangbroxd",
    "2027": "hwangbroxd",
    "1339": "hwangbroxd",
    "822": "hwangbroxd",
    "3981": "hwangbroxd",
    "1627": "hwangbroxd",
    "3700": "hwangbroxd",
    "116": "hwangbroxd",
    "2873": "hwangbroxd",
    "4416": "hwangbroxd",
    "1426": "hwangbroxd",
    "4106": "hwangbroxd",
    "3998": "hwangbroxd",
    "4456": "hwangbroxd",
    "2338": "hwangbroxd",
    "157": "hwangbroxd",
    "3456": "hwangbroxd",
    "1084": "hwangbroxd",
    "2090": "hwangbroxd",
    "1275": "hwangbroxd",
    "3266": "hwangbroxd",
    "2464": "hwangbroxd",
    "3647": "hwangbroxd",
    "3705": "hwangbroxd",
    "1837": "hwangbroxd",
    "225": "hwangbroxd",
    "1812": "hwangbroxd",
    "1791": "hwangbroxd",
    "3631": "hwangbroxd",
    "2014": "hwangbroxd",
    "4041": "hwangbroxd",
    "4849": "hwangbroxd",
    "1136": "hwangbroxd",
    "3876": "hwangbroxd",
    "1571": "hwangbroxd",
    "1201": "hwangbroxd",
    "3063": "hwangbroxd",
    "2915": "hwangbroxd",
    "4295": "hwangbroxd",
    "2266": "hwangbroxd",
    "1841": "hwangbroxd",
    "3527": "hwangbroxd",
    "4543": "hwangbroxd",
    "1398": "hwangbroxd",
    "1222": "hwangbroxd",
    "950": "hwangbroxd",
    "1867": "hwangbroxd",
    "1683": "hwangbroxd",
    "4045": "hwangbroxd",
    "4021": "hwangbroxd",
    "4845": "hwangbroxd",
    "1019": "hwangbroxd",
    "4427": "hwangbroxd",
    "3650": "hwangbroxd",
    "2496": "hwangbroxd",
    "3853": "hwangbroxd",
    "2616": "hwangbroxd",
    "1202": "hwangbroxd",
    "4164": "hwangbroxd",
    "2258": "hwangbroxd",
    "4299": "hwangbroxd",
    "3835": "hwangbroxd",
    "4505": "hwangbroxd",
    "3911": "hwangbroxd",
    "4862": "hwangbroxd",
    "4750": "hwangbroxd",
    "499": "hwangbroxd",
    "1200": "hwangbroxd",
    "3333": "hwangbroxd",
    "3943": "hwangbroxd",
    "2378": "hwangbroxd",
    "661": "hwangbroxd",
    "1959": "hwangbroxd",
    "1305": "hwangbroxd",
    "4464": "hwangbroxd",
    "1127": "hwangbroxd",
    "2762": "hwangbroxd",
    "4302": "hwangbroxd",
    "3910": "hwangbroxd",
    "1671": "hwangbroxd",
    "3114": "hwangbroxd",
    "3808": "hwangbroxd",
    "3060": "hwangbroxd",
    "2899": "hwangbroxd",
    "4193": "hwangbroxd",
    "1670": "hwangbroxd",
    "2364": "hwangbroxd",
    "1502": "hwangbroxd",
    "4766": "hwangbroxd",
    "315": "hwangbroxd",
    "533": "hwangbroxd",
    "428": "hwangbroxd",
    "4387": "hwangbroxd",
    "1618": "hwangbroxd",
    "3524": "hwangbroxd",
    "4324": "hwangbroxd",
    "1749": "hwangbroxd",
    "1975": "hwangbroxd",
    "1987": "hwangbroxd",
    "2567": "hwangbroxd",
    "4499": "hwangbroxd",
    "2900": "hwangbroxd",
    "1846": "hwangbroxd",
    "527": "hwangbroxd",
    "3689": "hwangbroxd",
    "4364": "hwangbroxd",
    "3947": "hwangbroxd",
    "748": "hwangbroxd",
    "4947": "hwangbroxd",
    "3614": "hwangbroxd",
    "2751": "hwangbroxd",
    "1151": "hwangbroxd",
    "788": "hwangbroxd",
    "3341": "hwangbroxd",
    "1137": "hwangbroxd",
    "1527": "hwangbroxd",
    "1581": "hwangbroxd",
    "750": "hwangbroxd",
    "380": "hwangbroxd",
    "3441": "hwangbroxd",
    "3259": "hwangbroxd",
    "2761": "hwangbroxd",
    "2563": "hwangbroxd",
    "3011": "hwangbroxd",
    "2690": "hwangbroxd",
    "4923": "hwangbroxd",
    "4696": "hwangbroxd",
    "3322": "hwangbroxd",
    "2791": "hwangbroxd",
    "3428": "hwangbroxd",
    "4275": "hwangbroxd",
    "68": "hwangbroxd",
    "2869": "hwangbroxd",
    "4571": "hwangbroxd",
    "3588": "hwangbroxd",
    "3899": "hwangbroxd",
    "3091": "hwangbroxd",
    "3967": "hwangbroxd",
    "1210": "hwangbroxd",
    "589": "hwangbroxd",
    "1040": "hwangbroxd",
    "1160": "hwangbroxd",
    "2513": "hwangbroxd",
    "1993": "hwangbroxd",
    "2248": "hwangbroxd",
    "1931": "hwangbroxd",
    "3337": "hwangbroxd",
    "2161": "hwangbroxd",
    "1243": "hwangbroxd",
    "254": "hwangbroxd",
    "2310": "hwangbroxd",
    "258": "hwangbroxd",
    "2894": "hwangbroxd",
    "615": "hwangbroxd",
    "2831": "hwangbroxd",
    "4768": "hwangbroxd",
    "4469": "hwangbroxd",
    "2499": "hwangbroxd",
    "1157": "hwangbroxd",
    "2021": "hwangbroxd",
    "3702": "hwangbroxd",
    "2322": "hwangbroxd",
    "1142": "hwangbroxd",
    "4390": "hwangbroxd",
    "2998": "hwangbroxd",
    "988": "hwangbroxd",
    "405": "hwangbroxd",
    "3208": "hwangbroxd",
    "3327": "hwangbroxd",
    "4727": "hwangbroxd",
    "2277": "hwangbroxd",
    "1476": "hwangbroxd",
    "2302": "hwangbroxd",
    "2671": "hwangbroxd",
    "1234": "hwangbroxd",
    "4310": "hwangbroxd",
    "378": "hwangbroxd",
    "4231": "hwangbroxd",
    "643": "hwangbroxd",
    "3426": "hwangbroxd",
    "1583": "hwangbroxd",
    "3577": "hwangbroxd",
    "3739": "hwangbroxd",
    "4197": "hwangbroxd",
    "1644": "hwangbroxd",
    "138": "hwangbroxd",
    "2465": "hwangbroxd",
    "1890": "hwangbroxd",
    "1429": "hwangbroxd",
    "1520": "hwangbroxd",
    "3960": "hwangbroxd",
    "1277": "hwangbroxd",
    "3196": "hwangbroxd",
    "2433": "hwangbroxd",
    "2681": "hwangbroxd",
    "3388": "hwangbroxd",
    "2892": "hwangbroxd",
    "2062": "hwangbroxd",
    "349": "hwangbroxd",
    "4886": "hwangbroxd",
    "4634": "hwangbroxd",
    "1913": "hwangbroxd",
    "4733": "hwangbroxd",
    "4362": "hwangbroxd",
    "1060": "hwangbroxd",
    "330": "hwangbroxd",
    "295": "hwangbroxd",
    "3933": "hwangbroxd",
    "4519": "hwangbroxd",
    "3763": "hwangbroxd",
    "3375": "hwangbroxd",
    "985": "hwangbroxd",
    "2247": "hwangbroxd",
    "3795": "hwangbroxd",
    "62": "hwangbroxd",
    "2655": "hwangbroxd",
    "3417": "hwangbroxd",
    "79": "hwangbroxd",
    "2102": "hwangbroxd",
    "3344": "hwangbroxd",
    "4180": "hwangbroxd",
    "200": "hwangbroxd",
    "3447": "hwangbroxd",
    "2115": "hwangbroxd",
    "1446": "hwangbroxd",
    "4871": "hwangbroxd",
    "20": "hwangbroxd",
    "1961": "hwangbroxd",
    "1929": "hwangbroxd",
    "601": "hwangbroxd",
    "3755": "hwangbroxd",
    "4413": "hwangbroxd",
    "262": "hwangbroxd",
    "1523": "hwangbroxd",
    "4067": "hwangbroxd",
    "4076": "hwangbroxd",
    "2068": "hwangbroxd",
    "3713": "hwangbroxd",
    "189": "hwangbroxd",
    "4177": "hwangbroxd",
    "2151": "hwangbroxd",
    "2470": "hwangbroxd",
    "2175": "hwangbroxd",
    "4666": "hwangbroxd",
    "2809": "hwangbroxd",
    "1786": "hwangbroxd",
    "4530": "hwangbroxd",
    "1483": "hwangbroxd",
    "4381": "hwangbroxd",
    "3486": "hwangbroxd",
    "3939": "hwangbroxd",
    "326": "hwangbroxd",
    "361": "hwangbroxd",
    "2412": "hwangbroxd",
    "1140": "hwangbroxd",
    "727": "hwangbroxd",
    "847": "hwangbroxd",
    "450": "hwangbroxd",
    "3254": "hwangbroxd",
    "4691": "hwangbroxd",
    "1493": "hwangbroxd",
    "1457": "hwangbroxd",
    "3406": "hwangbroxd",
    "1657": "hwangbroxd",
    "4069": "hwangbroxd",
    "242": "hwangbroxd",
    "2979": "hwangbroxd",
    "2365": "hwangbroxd",
    "2239": "hwangbroxd",
    "1340": "hwangbroxd",
    "4071": "hwangbroxd",
    "1697": "hwangbroxd",
    "2842": "hwangbroxd",
    "2917": "hwangbroxd",
    "2001": "hwangbroxd",
    "1767": "hwangbroxd",
    "4549": "hwangbroxd",
    "2146": "hwangbroxd",
    "4911": "hwangbroxd",
    "555": "hwangbroxd",
    "3823": "hwangbroxd",
    "1766": "hwangbroxd",
    "3750": "hwangbroxd",
    "1912": "hwangbroxd",
    "3460": "hwangbroxd",
    "3643": "hwangbroxd",
    "4417": "hwangbroxd",
    "2263": "hwangbroxd",
    "4451": "hwangbroxd",
    "4937": "hwangbroxd",
    "4809": "hwangbroxd",
    "1035": "hwangbroxd",
    "999": "hwangbroxd",
    "2328": "hwangbroxd",
    "1330": "hwangbroxd",
    "4752": "hwangbroxd",
    "549": "hwangbroxd",
    "4472": "hwangbroxd",
    "1175": "hwangbroxd",
    "3326": "hwangbroxd",
    "3214": "hwangbroxd",
    "715": "hwangbroxd",
    "3632": "hwangbroxd",
    "2250": "hwangbroxd",
    "3703": "hwangbroxd",
    "1189": "hwangbroxd",
    "2535": "hwangbroxd",
    "3146": "hwangbroxd",
    "1016": "hwangbroxd",
    "299": "hwangbroxd",
    "1190": "hwangbroxd",
    "1893": "hwangbroxd",
    "4463": "hwangbroxd",
    "3953": "hwangbroxd",
    "3895": "hwangbroxd",
    "3095": "hwangbroxd",
    "1379": "hwangbroxd",
    "3889": "hwangbroxd",
    "1206": "hwangbroxd",
    "1866": "hwangbroxd",
    "4847": "hwangbroxd",
    "2709": "hwangbroxd",
    "4874": "hwangbroxd",
    "1992": "hwangbroxd",
    "96": "hwangbroxd",
    "1280": "hwangbroxd",
    "1237": "hwangbroxd",
    "318": "hwangbroxd",
    "3331": "hwangbroxd",
    "4705": "hwangbroxd",
    "3528": "hwangbroxd",
    "2341": "hwangbroxd",
    "463": "hwangbroxd",
    "3574": "hwangbroxd",
    "2229": "hwangbroxd",
    "304": "hwangbroxd"
}